searegion_detection/__init__.py
searegion_detection/pandaseavox.py
searegion_detection/queryregion.py
searegion_detection-0.0.5.dist-info/METADATA
searegion_detection-0.0.5.dist-info/WHEEL
searegion_detection-0.0.5.dist-info/licenses/LICENSE
searegion_detection-0.0.5.dist-info/RECORD
